odoo/addons/product_tax_multicompany_default/README.rst
odoo/addons/product_tax_multicompany_default/__init__.py
odoo/addons/product_tax_multicompany_default/__manifest__.py
odoo/addons/product_tax_multicompany_default/i18n/de.po
odoo/addons/product_tax_multicompany_default/i18n/es.po
odoo/addons/product_tax_multicompany_default/i18n/fr.po
odoo/addons/product_tax_multicompany_default/i18n/product_tax_multicompany_default.pot
odoo/addons/product_tax_multicompany_default/models/__init__.py
odoo/addons/product_tax_multicompany_default/models/product.py
odoo/addons/product_tax_multicompany_default/static/description/icon.png
odoo/addons/product_tax_multicompany_default/tests/__init__.py
odoo/addons/product_tax_multicompany_default/tests/test_product_tax_multicompany.py
odoo/addons/product_tax_multicompany_default/views/product_template_view.xml
odoo11_addon_product_tax_multicompany_default-11.0.1.0.0.99.dev4.dist-info/METADATA
odoo11_addon_product_tax_multicompany_default-11.0.1.0.0.99.dev4.dist-info/RECORD
odoo11_addon_product_tax_multicompany_default-11.0.1.0.0.99.dev4.dist-info/WHEEL
odoo11_addon_product_tax_multicompany_default-11.0.1.0.0.99.dev4.dist-info/top_level.txt
